{
  "generated_at": "2026-02-27T05:33:16.008551+08:00",
  "total_titles_processed": 581,
  "failed_sources": [],
  "trends": [
    {
      "keyword_group": "汽车",
      "match_count": 1,
      "titles": [
        {
          "title": "2025全球汽车销量TOP10出炉！中国品牌“三强聚首” 比亚迪排名创新高",
          "url": "https://www.cls.cn/detail/2296081",
          "source": "财联社热门",
          "ranks": [
            3,
            4
          ],
          "is_new": false,
          "appearance_count": 7,
          "time_info": "[00时58分 ~ 05时33分]"
        }
      ]
    }
  ],
  "report_image_url": "https://aidanhu.github.io/TrendRadar/img/news.jpg"
}