{
  "generated_at": "2026-01-23T07:22:21.127718+08:00",
  "total_titles_processed": 753,
  "failed_sources": [],
  "trends": [
    {
      "keyword_group": "汽车",
      "match_count": 3,
      "titles": [
        {
          "title": "据CNN：美国汽车工人联合会正接近与通用汽车和斯特兰蒂斯达成协议。",
          "url": "https://flash.jin10.com/detail/20260123025541582800",
          "source": "金十数据",
          "ranks": [
            3,
            19
          ],
          "is_new": false,
          "appearance_count": 2,
          "time_info": "[03时25分 ~ 04时28分]"
        },
        {
          "title": "重庆“收复”汽车第一城",
          "url": "https://www.baidu.com/s?wd=%E9%87%8D%E5%BA%86%E2%80%9C%E6%94%B6%E5%A4%8D%E2%80%9D%E6%B1%BD%E8%BD%A6%E7%AC%AC%E4%B8%80%E5%9F%8E",
          "source": "百度热搜",
          "ranks": [
            20
          ],
          "is_new": false,
          "appearance_count": 2,
          "time_info": "[05时24分 ~ 06时23分]"
        },
        {
          "title": "周四（1月22日），彭博电动汽车价格回报指数涨1.68%，报3685.88点。",
          "url": "https://wallstreetcn.com/livenews/3042310",
          "source": "华尔街见闻-快讯",
          "ranks": [
            22
          ],
          "is_new": false,
          "appearance_count": 1,
          "time_info": "06时23分"
        }
      ]
    }
  ],
  "report_image_url": "https://aidanhu.github.io/TrendRadar/img/news.jpg"
}